PythonAI/GeneticAlgorithm.py
PythonAI/NeuralNetwork.py
PythonAI/__init__.py
PythonAI/setup.py
PythonAI/dep/GeneticAlgorithm.py
PythonAI/dep/NeuralNetwork.py
PythonAI/dep/__init__.py
PythonAI-0.0.1.dist-info/LICENSE
PythonAI-0.0.1.dist-info/METADATA
PythonAI-0.0.1.dist-info/WHEEL
PythonAI-0.0.1.dist-info/top_level.txt
PythonAI-0.0.1.dist-info/RECORD
